geocoordinates/__init__.py
geocoordinates/geocoordinates.py
geocoordinates/lla_coordinate_time_series.csv
geocoordinates-0.1.22.dist-info/WHEEL
geocoordinates-0.1.22.dist-info/METADATA
geocoordinates-0.1.22.dist-info/RECORD
