Metadata-Version: 2.1
Name: geocoordinates
Version: 0.1.22
Summary: 
Author: kathesch
Author-email: katherinegruenewald@gmail.com
Requires-Python: >=3.10,<4.0
Classifier: Programming Language :: Python :: 3
Classifier: Programming Language :: Python :: 3.10
Requires-Dist: numpy (>=1.23.3,<2.0.0)
Requires-Dist: pandas (>=1.5.0,<2.0.0)
